tuya_ble/__init__.py
tuya_ble/const.py
tuya_ble/exceptions.py
tuya_ble/manager.py
tuya_ble/tuya_ble.py
tuya_ble-0.1.0.dist-info/AUTHORS.rst
tuya_ble-0.1.0.dist-info/LICENSE
tuya_ble-0.1.0.dist-info/METADATA
tuya_ble-0.1.0.dist-info/WHEEL
tuya_ble-0.1.0.dist-info/top_level.txt
tuya_ble-0.1.0.dist-info/RECORD
