Metadata-Version: 2.1
Name: tuya-ble
Version: 0.1.0
Summary: Library to control Tuya BLE devices
Home-page: https://github.com/PlusPlus-ua/tuya_ble
Author: Oleksander Plias
Author-email: alexplas@gmail.com
License: MIT license
Keywords: tuya_ble
Classifier: Development Status :: 2 - Pre-Alpha
Classifier: Intended Audience :: Developers
Classifier: License :: OSI Approved :: MIT License
Classifier: Natural Language :: English
Classifier: Programming Language :: Python :: 3
Classifier: Programming Language :: Python :: 3.6
Classifier: Programming Language :: Python :: 3.7
Classifier: Programming Language :: Python :: 3.8
Requires-Python: >=3.6
License-File: LICENSE
License-File: AUTHORS.rst
Requires-Dist: asyncio
Requires-Dist: bleak
Requires-Dist: bleak-retry-connector
